{"start_time":1622465341000,"end_time":1622467560000,"created_at":1622465340000,"updated_at":1638541759000,"start_time_timezone_offset":10800000,"end_time_timezone_offset":10800000,"distance":5984,"duration":2218230,"elevation_gain":7,"elevation_loss":65,"average_speed":9.713,"calories":89,"longitude":30.683443,"latitude":36.9229,"max_speed":26.865234,"pause_duration":0,"duration_per_km":370694,"temperature":24.0,"pulse_avg":0,"pulse_max":0,"manual":false,"edited":false,"completed":true,"live_tracking_active":false,"live_tracking_enabled":true,"cheering_enabled":true,"indoor":false,"id":"0ae7089f-fdb2-4d1a-8b5e-ca7520adeafc","weather_condition_id":"2","sport_type_id":"3"}